{
  "name": "Vitriolic Sphere",
  "type": "spell",
  "img": "icons/magic/fire/projectile-fireball-smoke-large-green.webp",
  "data": {
    "description": {
      "value": "<div class=\"rd__b  rd__b--3\">\n<p>You point at a location within range, and a glowing 1-foot-diameter ball of emerald acid streaks there and explodes in a 20-foot-radius sphere. Each creature in that area must make a Dexterity saving throw. On a failed save, a creature takes [[/r 10d4]] acid damage and another [[/r 5d4]] acid damage at the end of its next turn. On a successful save, a creature takes half the initial damage and no damage at the end of its next turn.</p>\n<div class=\"rd__spc-inline-post\"> </div>\n</div>\n<div class=\"rd__b  rd__b--3\">\n<div class=\"rd__b  rd__b--3\"><span class=\"rd__h rd__h--3\" data-title-index=\"36\"> <span class=\"entry-title-inner\">At Higher Levels.</span></span>\n<p>When you cast this spell using a spell slot of 5th level or higher, the initial damage increases by [[/r 2d4]] for each slot level above 4th.</p>\n<div class=\"rd__spc-inline-post\"> </div>\n</div>\n<div class=\"rd__spc-inline-post\"> </div>\n</div>",
      "chat": "",
      "unidentified": ""
    },
    "source": "XGE pg. 170",
    "activation": {
      "type": "action",
      "cost": 1,
      "condition": ""
    },
    "duration": {
      "value": 2,
      "units": "round"
    },
    "target": {
      "value": 20,
      "width": null,
      "units": "ft",
      "type": "sphere"
    },
    "range": {
      "value": 150,
      "long": null,
      "units": "ft"
    },
    "uses": {
      "value": null,
      "max": "",
      "per": ""
    },
    "consume": {
      "type": "",
      "target": "",
      "amount": null
    },
    "ability": "",
    "actionType": "save",
    "attackBonus": 0,
    "chatFlavor": "",
    "critical": {
      "threshold": null,
      "damage": null
    },
    "damage": {
      "parts": [
        [
          "10d4",
          "acid"
        ]
      ],
      "versatile": ""
    },
    "formula": "",
    "save": {
      "ability": "dex",
      "dc": null,
      "scaling": "spell"
    },
    "level": 4,
    "school": "evo",
    "components": {
      "value": "",
      "vocal": true,
      "somatic": true,
      "material": true,
      "ritual": false,
      "concentration": false
    },
    "materials": {
      "value": "a drop of giant slug bile",
      "consumed": false,
      "cost": 0,
      "supply": 0
    },
    "preparation": {
      "mode": "prepared",
      "prepared": true
    },
    "scaling": {
      "mode": "level",
      "formula": "2d4"
    }
  },
  "effects": [
    {
      "_id": "l3FjnbXqZW5MYr9O",
      "changes": [
        {
          "key": "flags.midi-qol.OverTime",
          "mode": 5,
          "value": "turn=end,damageRoll=5d4,damageType=acid,removeCondition=true",
          "priority": "20"
        }
      ],
      "disabled": false,
      "duration": {
        "startTime": null,
        "rounds": 2
      },
      "icon": "systems/dnd5e/icons/spells/fireball-acid-2.jpg",
      "label": "Vitriolic Sphere",
      "transfer": false,
      "flags": {
        "dae": {
          "stackable": "none",
          "macroRepeat": "none",
          "specialDuration": [],
          "transfer": false
        },
        "dnd5e-helpers": {
          "rest-effect": "Ignore"
        },
        "ActiveAuras": {
          "isAura": false,
          "aura": "None",
          "radius": null,
          "alignment": "",
          "type": "",
          "ignoreSelf": false,
          "height": false,
          "hidden": false,
          "hostile": false,
          "onlyOnce": false
        }
      },
      "tint": null,
      "selectedKey": "StatusEffect"
    }
  ],
  "flags": {
    "srd5e": {
      "page": "spells.html",
      "source": "XGE",
      "hash": "vitriolic%20sphere_xge",
      "parentClassName": "Wizard",
      "parentClassSource": "PHB",
      "parentSubclassName": "School of Evocation",
      "parentSubclassSource": "PHB"
    },
    "enhanced-terrain-layer": {
      "multiple": 1,
      "min": 0,
      "max": 0,
      "environment": ""
    },
    "midi-qol": {
      "onUseMacroName": "[postActiveEffects]ItemMacro",
      "effectActivation": false
    },
    "enhancedcombathud": {
      "set3s": true,
      "set1p": false,
      "set2p": false,
      "set3p": false
    },
    "siftoolkit": {
      "SIFData": {
        "ignoreDuration": false,
        "texture": "",
        "useTexture": false,
        "alpha": 50,
        "coneOrigin": 1,
        "loopAnimations": false,
        "playTemplateAudio": false,
        "playDamageAudio": false,
        "clip": "",
        "volume": 100
      }
    },
    "core": {
      "sourceId": "Item.QB7QAF8XlWYielfM"
    },
    "cf": {
      "id": "temp_h5bw1kk8lkh",
      "path": "Stuff#/CF_SEP/Spells",
      "color": "#000000"
    },
    "ddbimporter": {
      "id": 138280,
      "definitionId": 2404,
      "entityTypeId": 435869154,
      "dndbeyond": {
        "lookup": "classSpell",
        "class": "Wizard",
        "level": 8,
        "characterClassId": 60721312,
        "spellLevel": 4,
        "ability": "int",
        "mod": 4,
        "dc": 15,
        "cantripBoost": false,
        "overrideDC": false,
        "id": 138280,
        "entityTypeId": 435869154,
        "healingBoost": 0,
        "usesSpellSlot": true
      },
      "sources": [
        {
          "sourceId": 4,
          "pageNumber": 170,
          "sourceType": 1
        }
      ],
      "tags": [
        "Damage"
      ],
      "version": "2.7.2",
      "pack": "world.override",
      "originalItemName": "Vitriolic Sphere",
      "replaced": true
    },
    "itemacro": {
      "macro": {
        "data": {
          "_id": null,
          "name": "Vitriolic Sphere",
          "type": "script",
          "author": "jM4h8qpyxwTpfNli",
          "img": "icons/svg/dice-target.svg",
          "scope": "global",
          "command": "const tactor = canvas.tokens.get(args[0].tokenId);\nconst templateObject = canvas.templates.placeables[canvas.templates.placeables.length - 1]\nnew Sequence()\n  .effect()\n    .file(\"jb2a.fire_bolt.green02\")\n    .atLocation(tactor)\n    .stretchTo({ x: templateObject.data.x, y: templateObject.data.y })\n    .waitUntilFinished(-750)\n  .effect()\n    .file(\"jb2a.fog_cloud.2.Green\")\n    .attachTo(templateObject)\n    .scaleToObject(1.1)\n    .opacity(0.5)\n    .persist()\n    .scaleIn(0.1, 200, {ease: \"easeOutQuint\", delay: 100})\n    .fadeOut(1000, {ease: \"easeInQuad\"})\n  .play()",
          "folder": null,
          "sort": 0,
          "permission": {
            "default": 0
          },
          "flags": {}
        }
      }
    },
    "autoanimations": {
      "killAnim": false,
      "below": false,
      "override": false,
      "targetToken": {
        "enable": false,
        "opacity": 1,
        "animLevel": false,
        "persistent": false,
        "name": "marker",
        "variant": "bubble",
        "color": "blue",
        "delayStart": 500,
        "loops": 1,
        "loopDelay": 250,
        "scale": 1,
        "enableCustom": false
      },
      "sourceToken": {
        "enable": false,
        "opacity": 1,
        "animLevel": false,
        "name": "a1",
        "variant": "",
        "color": "",
        "loops": 1,
        "loopDelay": 250,
        "scale": 1,
        "delayAfter": 500,
        "enableCustom": false
      },
      "allSounds": {
        "explosion": {
          "audioExplodeEnabled": false,
          "file": "",
          "delay": 100,
          "volume": 0.25
        },
        "item": {
          "enableAudio": false,
          "file": "",
          "delay": 100,
          "volume": 0.25
        }
      },
      "autoOverride": {
        "enable": false,
        "fireball": {
          "projectile": "firebolt",
          "projectileVariant": "01",
          "projectileColor": "darkgreen",
          "wait01": null,
          "explosion01Color": "greenorange",
          "explosion02Color": "blue",
          "afterEffect": false
        }
      },
      "version": 3,
      "animType": "preset",
      "animation": "fireball",
      "color": "darkgreen",
      "explosions": {
        "enable": true,
        "below": false,
        "radius": 4,
        "delay": 250,
        "animation": "explosion",
        "variant": "01",
        "color": "green",
        "enableCustom": true,
        "customPath": "modules/jaamod/AnimatedArt/Spells-Effects/cloudKill.webm"
      },
      "options": {
        "rangeType": "spell",
        "variant": "01",
        "repeat": 1,
        "delay": 250,
        "ammo": false,
        "removeTemplate": false,
        "tempType": "cone",
        "scale": 1,
        "opacity": 1,
        "enableCustom": false,
        "persistent": false
      },
      "audio": {
        "a01": {
          "enable": false,
          "file": "",
          "delay": 100,
          "volume": 0.25
        },
        "e01": {
          "enable": false,
          "file": "",
          "delay": 100,
          "volume": 0.25
        },
        "e02": {
          "enable": false
        },
        "s01": {
          "enable": false
        },
        "t01": {
          "enable": false
        }
      },
      "animLevel": false,
      "levels3d": {
        "type": "",
        "explosion": {
          "color01": "#ffffff",
          "color02": "#ffffff",
          "speed": null,
          "repeat": null,
          "delay": null,
          "scale": null,
          "alpha": null,
          "gravity": null,
          "mass": null,
          "life": null,
          "emittersize": null,
          "rate": null,
          "sprite": "modules/levels-3d-preview/assets/particles/dust.png"
        }
      },
      "fireball": {
        "projectile": "firebolt",
        "projectileVariant": "01",
        "projectileColor": "green",
        "wait01": null,
        "projectileRepeat": null,
        "projectileDelay": null,
        "explosion01": "outpulse01",
        "explosion01Variant": "01",
        "explosion01Color": "greenorange",
        "wait02": null,
        "explosion01Repeat": null,
        "explosion01Delay": null,
        "explosion01Scale": null,
        "explosion02": "a1",
        "explosion02Variant": "",
        "explosion02Color": "",
        "explosion02Repeat": null,
        "explosion02Delay": null,
        "explosion02Scale": null,
        "afterEffect": true,
        "wait03": null,
        "afterEffectPath": ""
      }
    },
    "exportSource": {
      "world": "Rime-of-the-Frost-Maiden",
      "system": "dnd5e",
      "coreVersion": "9.242",
      "systemVersion": "1.5.7"
    }
  }
}